{
	"parameterdescriptiondefaults":
	{
		"isPublic":true,
		"isBipolar":false,
		"toText":"unsignedZero",
		"name":"",
		"class":"",
		"min":0,
		"max":127,
		"isBool":false,
		"isDiscrete":false,
		"page":0,
		"step":0
	},
 	"parameterdescriptions":
 	[
 		{"page":0, "index":0, "name":"Version", "min":0, "max":1, "isPublic":false, "isDiscrete":true},

		// Osc 1
		{"index":1 , "name":"O1Octave"     , "min":16, "max":112, "step":12},
 		{"index":2 , "name":"O1Semi"       , "min":52, "max":76, "isBipolar":true, "toText":"signed"},
 		{"index":3 , "name":"O1Detune"     , "isBipolar":true},

 		{"index":5 , "name":"O1BendRange"  , "min":0, "max":122, "toText":"pbrange"},
 		{"index":6 , "name":"O1KeyTrack"   , "min":0, "max":76, "default":64, "toText":"keytrack76"},
 		{"index":7 , "name":"O1FmAmount"},

		// Osc 2
		{"index":12 , "name":"O2Octave"     , "min":16, "max":112, "step":12},
 		{"index":13 , "name":"O2Semi"       , "min":52, "max":76, "isBipolar":true, "toText":"signed"},
 		{"index":14 , "name":"O2Detune"     , "isBipolar":true},

 		{"index":16 , "name":"O2Sync"       , "min":0, "max":1, "toText":"offOn"},
 		{"index":17 , "name":"O2BendRange"  , "min":0, "max":122, "toText":"pbrange"},
 		{"index":18 , "name":"O2KeyTrack"   , "min":0, "max":76, "default":64, "toText":"keytrack76"},
 		{"index":19 , "name":"O2Link"       , "min":0, "max":1, "toText":"offOn"},

		// Wavetable
 		{"index":25, "name":"Wave", "isDiscrete":true, "toText":"waveType"},

		// Wave 1
 		{"index":26, "name":"W1StartW", "min":0 , "max":63, "toText":"waveStartWave"},
 		{"index":27, "name":"W1StartP", "min":0 , "max":127, "toText":"waveStartPhase"},
 		{"index":28, "name":"W1EnvAmount", "min":0 , "max":127, "isBipolar":true, "toText":"signed"},
 		{"index":29, "name":"W1EnvVelAmount", "min":0 , "max":127, "isBipolar":true, "toText":"signed"},
 		{"index":30, "name":"W1Keytrack", "min":0 , "max":127, "toText":"keytrack127"},
 		{"index":31, "name":"W1Limit", "min":0 , "max":1, "toText":"offOn"},

		// Wave 2
 		{"index":36, "name":"W2StartW", "min":0 , "max":63, "toText":"waveStartWave"},
 		{"index":37, "name":"W2StartP", "min":0 , "max":127, "toText":"waveStartPhase"},
 		{"index":38, "name":"W2EnvAmount", "min":0 , "max":127, "isBipolar":true, "toText":"signed"},
 		{"index":39, "name":"W2EnvVelAmount", "min":0 , "max":127, "isBipolar":true, "toText":"signed"},
 		{"index":40, "name":"W2Keytrack", "min":0 , "max":127, "toText":"keytrack127"},
 		{"index":41, "name":"W2Limit", "min":0 , "max":1, "toText":"offOn"},
 		{"index":42, "name":"W2Link", "min":0 , "max":1, "toText":"offOn"},

		// Mixer
 		{"index":47, "name":"MixW1"},
 		{"index":48, "name":"MixW2"},
 		{"index":49, "name":"MixRingMod"},
 		{"index":50, "name":"MixNoise"},
 		{"index":51, "name":"MixExternal"},
		
 		{"index":53, "name":"Aliasing", "min":0, "max":5, "toText":"aliasing"},
 		{"index":54, "name":"TimeQuant", "min":0, "max":5, "toText":"timeQuant"},
 		{"index":55, "name":"Clipping", "min":0, "max":1, "toText":"clipping"},

 		{"index":57, "name":"Accuracy", "min":0, "max":1, "toText":"accuracy"},

 		{"index":58, "name":"PlayParamA", "min":0, "max":82, "isDiscrete":true, "toText":"playParameter"},
 		{"index":59, "name":"PlayParamB", "min":0, "max":82, "isDiscrete":true, "toText":"playParameter"},
 		{"index":60, "name":"PlayParamC", "min":0, "max":82, "isDiscrete":true, "toText":"playParameter"},
 		{"index":61, "name":"PlayParamD", "min":0, "max":82, "isDiscrete":true, "toText":"playParameter"},

		// Filters
 		{"index":62, "name":"F1Cutoff"},
 		{"index":63, "name":"F1Resonance"},
 		{"index":64, "name":"F1Type", "min":0, "max":9, "isDiscrete":true, "toText":"filter1Type"},
 		{"index":65, "name":"F1KeyTrack", "toText":"keytrack127"},
 		{"index":66, "name":"F1EnvAmount", "toText":"signed", "default":64, "isBipolar":true},
 		{"index":67, "name":"F1EnvVelAmount", "toText":"signed", "default":64, "isBipolar":true},

 		{"index":70, "name":"F1ContextSensitive"},

 		{"index":73, "name":"F2Cutoff"},
 		{"index":74, "name":"F2Type", "min":0, "max":1, "isDiscrete":true, "toText":"filter2Type"},
 		{"index":75, "name":"F2KeyTrack", "toText":"keytrack127"},

		{"index":76, "name":"EffectType", "min":0, "max":34, "toText":"effectType", "isDiscrete":true},

		// Amp
 		{"index":77, "name":"AmpVolume"},
		
 		{"index":79, "name":"AmpVelocity", "isBipolar":true, "toText":"signed"},
 		{"index":80, "name":"AmpKeytrack", "isBipolar":true, "toText":"keytrack127"},

 		{"index":81, "name":"EffectParamA"},
 		
		{"index":82, "name":"ChorusEnabled", "min":0, "max":1, "isBool":true, "toText":"offOn"},
 		
		{"index":83, "name":"EffectParamB"},

 		{"index":84, "name":"Pan", "isBipolar":true, "toText":"pan"},
 		{"index":85, "name":"PanKeytrack", "isBipolar":true, "toText":"keytrack127"},
 		{"index":86, "name":"EffectParamC"},
		
		// Glide
 		{"index":87, "name":"GlideEnabled", "min":0, "max":1, "isBool":true, "toText":"offOn"},
 		{"index":88, "name":"GlideType", "min":0, "max":3, "toText":"glideType", "isDiscrete":true},
 		{"index":89, "name":"GlideMode", "min":0, "max":1, "toText":"glideMode", "isDiscrete":true},
 		{"index":90, "name":"GlideTime"},

		// Arp
 		{"index":92, "name":"ArpMode", "min":0, "max":2, "toText":"arpMode", "isDiscrete":true},
 		{"index":93, "name":"ArpTempo", "min":1, "max":127, "toText":"arpTempo"},
 		{"index":94, "name":"ArpClock", "min":0, "max":15, "toText":"arpClock", "isDiscrete":true},
 		{"index":95, "name":"ArpRange", "min":1, "max":10, "isDiscrete":true},
 		{"index":96, "name":"ArpPattern", "min":0, "max":16, "toText":"arpPattern", "isDiscrete":true},
 		{"index":97, "name":"ArpDirection", "min":0, "max":3, "toText":"arpDirection", "isDiscrete":true},
 		{"index":98, "name":"ArpNoteOrder", "min":0, "max":3, "toText":"arpNoteOrder", "isDiscrete":true},
 		{"index":99, "name":"ArpVelocity", "min":0, "max":1, "toText":"arpVelocity", "isDiscrete":true},
 		{"index":100, "name":"ArpReset", "min":0, "max":1, "toText":"offOn", "isDiscrete":true},
 		{"index":101, "name":"ArpUserPatternLength", "min":0, "max":15, "isDiscrete":true, "toText":"unsignedOne"},

 		{"index":102, "name":"ArpUserPattern1" , "min":0, "max":1, "isBool":true},
 		{"index":102, "name":"ArpUserPattern2" , "min":0, "max":1, "isBool":true},
 		{"index":102, "name":"ArpUserPattern3" , "min":0, "max":1, "isBool":true},
 		{"index":102, "name":"ArpUserPattern4" , "min":0, "max":1, "isBool":true},
 		{"index":103, "name":"ArpUserPattern5" , "min":0, "max":1, "isBool":true},
 		{"index":103, "name":"ArpUserPattern6" , "min":0, "max":1, "isBool":true},
 		{"index":103, "name":"ArpUserPattern7" , "min":0, "max":1, "isBool":true},
 		{"index":103, "name":"ArpUserPattern8" , "min":0, "max":1, "isBool":true},
 		{"index":104, "name":"ArpUserPattern9" , "min":0, "max":1, "isBool":true},
 		{"index":104, "name":"ArpUserPattern10", "min":0, "max":1, "isBool":true},
 		{"index":104, "name":"ArpUserPattern11", "min":0, "max":1, "isBool":true},
 		{"index":104, "name":"ArpUserPattern12", "min":0, "max":1, "isBool":true},
 		{"index":105, "name":"ArpUserPattern13", "min":0, "max":1, "isBool":true},
 		{"index":105, "name":"ArpUserPattern14", "min":0, "max":1, "isBool":true},
 		{"index":105, "name":"ArpUserPattern15", "min":0, "max":1, "isBool":true},
 		{"index":105, "name":"ArpUserPattern16", "min":0, "max":1, "isBool":true},

 		{"index":108, "name":"AllocationMode", "min":0, "max":1, "toText":"allocationMode", "isDiscrete":true},
 		{"index":109, "name":"Assignment", "min":0, "max":2, "toText":"assignment", "isDiscrete":true},
 		{"index":110, "name":"Detune"},

		{"index":112, "name":"DePan"},

		{"index":113, "name":"F1EnvAttack"},
		{"index":114, "name":"F1EnvDecay"},
		{"index":115, "name":"F1EnvSustain"},
		{"index":116, "name":"F1EnvRelease"},
		{"index":117, "name":"F1EnvTrigger", "min":0, "max":2, "isDiscrete":true, "toText":"envTrigger"},

		{"index":119, "name":"AmpEnvAttack"},
		{"index":120, "name":"AmpEnvDecay"},
		{"index":121, "name":"AmpEnvSustain"},
		{"index":122, "name":"AmpEnvRelease"},
		{"index":123, "name":"AmpEnvTrigger", "min":0, "max":2, "isDiscrete":true, "toText":"envTrigger"},

		{"index":125, "name":"WaveEnvTime1"},	{"index":126, "name":"WaveEnvLevel1"},
		{"index":127, "name":"WaveEnvTime2"},	{"index":128, "name":"WaveEnvLevel2"},
		{"index":129, "name":"WaveEnvTime3"},	{"index":130, "name":"WaveEnvLevel3"},
		{"index":131, "name":"WaveEnvTime4"},	{"index":132, "name":"WaveEnvLevel4"},
		{"index":133, "name":"WaveEnvTime5"},	{"index":134, "name":"WaveEnvLevel5"},
		{"index":135, "name":"WaveEnvTime6"},	{"index":136, "name":"WaveEnvLevel6"},
		{"index":137, "name":"WaveEnvTime7"},	{"index":138, "name":"WaveEnvLevel7"},
		{"index":139, "name":"WaveEnvTime8"},	{"index":140, "name":"WaveEnvLevel8"},

		{"index":141, "name":"WaveEnvTrigger", "min":0, "max":2, "isDiscrete":true, "toText":"envTrigger"},

		{"index":142, "name":"WaveKeyOnLoop", "min":0, "max":1, "toText":"offOn", "isBool":true},
		{"index":143, "name":"WaveKeyOnLoopStart", "min":0, "max":7, "isDiscrete":true},
		{"index":144, "name":"WaveKeyOnLoopEnd", "min":0, "max":7, "isDiscrete":true},

		{"index":145, "name":"WaveKeyOffLoop", "min":0, "max":1, "toText":"offOn", "isBool":true},
		{"index":146, "name":"WaveKeyOffLoopStart", "min":0, "max":7, "isDiscrete":true},
		{"index":147, "name":"WaveKeyOffLoopEnd", "min":0, "max":7, "isDiscrete":true},

		{"index":149, "name":"FreeEnvTime1"},		{"index":150, "name":"FreeEnvLevel1", "isBipolar":true, "toText":"signed", "default":64},
		{"index":151, "name":"FreeEnvTime2"},		{"index":152, "name":"FreeEnvLevel2", "isBipolar":true, "toText":"signed", "default":64},
		{"index":153, "name":"FreeEnvTime3"},		{"index":154, "name":"FreeEnvLevel3", "isBipolar":true, "toText":"signed", "default":64},
		{"index":155, "name":"FreeEnvReleaseTime"},	{"index":156, "name":"FreeEnvReleaseLevel", "isBipolar":true, "toText":"signed", "default":64},
		{"index":157, "name":"FreeEnvTrigger", "min":0, "max":2, "isDiscrete":true, "toText":"envTrigger"},

		// LFO 1
 		{"index":159, "name":"Lfo1Rate"},
 		{"index":160, "name":"Lfo1Shape", "min":0, "max":5, "isDiscrete":true, "toText":"lfoShape"},
 		{"index":161, "name":"Lfo1Delay"},
 		{"index":162, "name":"Lfo1Sync", "min":0 , "max":3, "isDiscrete":true, "toText":"lfoSync"},
 		{"index":163, "name":"Lfo1Symmetry", "isBipolar":true, "toText":"signed"},
 		{"index":164, "name":"Lfo1Humanize"},

 		{"index":166, "name":"Lfo2Rate"},
 		{"index":167, "name":"Lfo2Shape", "min":0, "max":5, "isDiscrete":true, "toText":"lfoShape"},
 		{"index":168, "name":"Lfo2Delay"},
 		{"index":169, "name":"Lfo2Sync", "min":0 , "max":3, "isDiscrete":true, "toText":"lfoSync"},
 		{"index":170, "name":"Lfo2Symmetry", "isBipolar":true, "toText":"signed"},
 		{"index":171, "name":"Lfo2Humanize"},
 		{"index":172, "name":"Lfo2Phase", "toText":"lfoPhase"},

		// Modifiers
 		{"index":174, "name":"ModDelaySource", "min":0, "max":31, "isDiscrete":true, "toText":"modSource"},
 		{"index":175, "name":"ModDelayTime"},

 		{"index":176, "name":"Mod1Source1", "min":0, "max":31, "isDiscrete":true, "toText":"modSource"},
 		{"index":177, "name":"Mod1Source2", "min":0, "max":31, "isDiscrete":true, "toText":"modSource"},
 		{"index":178, "name":"Mod1Type",    "min":0, "max":15, "isDiscrete":true, "toText":"modType"  },
 		{"index":179, "name":"Mod1Parameter"                                                          },
 		{"index":180, "name":"Mod2Source1", "min":0, "max":31, "isDiscrete":true, "toText":"modSource"},
 		{"index":181, "name":"Mod2Source2", "min":0, "max":31, "isDiscrete":true, "toText":"modSource"},
 		{"index":182, "name":"Mod2Type",    "min":0, "max":15, "isDiscrete":true, "toText":"modType"  },
 		{"index":183, "name":"Mod2Parameter"                                                          },
 		{"index":184, "name":"Mod3Source1", "min":0, "max":31, "isDiscrete":true, "toText":"modSource"},
 		{"index":185, "name":"Mod3Source2", "min":0, "max":31, "isDiscrete":true, "toText":"modSource"},
 		{"index":186, "name":"Mod3Type",    "min":0, "max":15, "isDiscrete":true, "toText":"modType"  },
 		{"index":187, "name":"Mod3Parameter"                                                          },
 		{"index":188, "name":"Mod4Source1", "min":0, "max":31, "isDiscrete":true, "toText":"modSource"},
 		{"index":189, "name":"Mod4Source2", "min":0, "max":31, "isDiscrete":true, "toText":"modSource"},
 		{"index":190, "name":"Mod4Type",    "min":0, "max":15, "isDiscrete":true, "toText":"modType"  },
 		{"index":191, "name":"Mod4Parameter"                                                          },
		
		// Mod Matrix
 		{"index":192, "name":"Slot1Source"      , "min":0, "max":31, "isDiscrete":true, "toText":"modSource"},
 		{"index":193, "name":"Slot1Amount"      , "default":64, "isBipolar":true                            },
 		{"index":194, "name":"Slot1Destination" , "min":0, "max":30, "isDiscrete":true, "toText":"modDest"  },
 		{"index":195, "name":"Slot2Source"      , "min":0, "max":31, "isDiscrete":true, "toText":"modSource"},
 		{"index":196, "name":"Slot2Amount"      , "default":64, "isBipolar":true                            },
 		{"index":197, "name":"Slot2Destination" , "min":0, "max":30, "isDiscrete":true, "toText":"modDest"  },
 		{"index":198, "name":"Slot3Source"      , "min":0, "max":31, "isDiscrete":true, "toText":"modSource"},
 		{"index":199, "name":"Slot3Amount"      , "default":64, "isBipolar":true                            },
 		{"index":200, "name":"Slot3Destination" , "min":0, "max":30, "isDiscrete":true, "toText":"modDest"  },
 		{"index":201, "name":"Slot4Source"      , "min":0, "max":31, "isDiscrete":true, "toText":"modSource"},
 		{"index":202, "name":"Slot4Amount"      , "default":64, "isBipolar":true                            },
 		{"index":203, "name":"Slot4Destination" , "min":0, "max":30, "isDiscrete":true, "toText":"modDest"  },
 		{"index":204, "name":"Slot5Source"      , "min":0, "max":31, "isDiscrete":true, "toText":"modSource"},
 		{"index":205, "name":"Slot5Amount"      , "default":64, "isBipolar":true                            },
 		{"index":206, "name":"Slot5Destination" , "min":0, "max":30, "isDiscrete":true, "toText":"modDest"  },
 		{"index":207, "name":"Slot6Source"      , "min":0, "max":31, "isDiscrete":true, "toText":"modSource"},
 		{"index":208, "name":"Slot6Amount"      , "default":64, "isBipolar":true                            },
 		{"index":209, "name":"Slot6Destination" , "min":0, "max":30, "isDiscrete":true, "toText":"modDest"  },
 		{"index":210, "name":"Slot7Source"      , "min":0, "max":31, "isDiscrete":true, "toText":"modSource"},
 		{"index":211, "name":"Slot7Amount"      , "default":64, "isBipolar":true                            },
 		{"index":212, "name":"Slot7Destination" , "min":0, "max":30, "isDiscrete":true, "toText":"modDest"  },
 		{"index":213, "name":"Slot8Source"      , "min":0, "max":31, "isDiscrete":true, "toText":"modSource"},
 		{"index":214, "name":"Slot8Amount"      , "default":64, "isBipolar":true                            },
 		{"index":215, "name":"Slot8Destination" , "min":0, "max":30, "isDiscrete":true, "toText":"modDest"  },
 		{"index":216, "name":"Slot9Source"      , "min":0, "max":31, "isDiscrete":true, "toText":"modSource"},
 		{"index":217, "name":"Slot9Amount"      , "default":64, "isBipolar":true                            },
 		{"index":218, "name":"Slot9Destination" , "min":0, "max":30, "isDiscrete":true, "toText":"modDest"  },
 		{"index":219, "name":"Slot10Source"     , "min":0, "max":31, "isDiscrete":true, "toText":"modSource"},
 		{"index":220, "name":"Slot10Amount"     , "default":64, "isBipolar":true                            },
 		{"index":221, "name":"Slot10Destination", "min":0, "max":30, "isDiscrete":true, "toText":"modDest"  },
 		{"index":222, "name":"Slot11Source"     , "min":0, "max":31, "isDiscrete":true, "toText":"modSource"},
 		{"index":223, "name":"Slot11Amount"     , "default":64, "isBipolar":true                            },
 		{"index":224, "name":"Slot11Destination", "min":0, "max":30, "isDiscrete":true, "toText":"modDest"  },
 		{"index":225, "name":"Slot12Source"     , "min":0, "max":31, "isDiscrete":true, "toText":"modSource"},
 		{"index":226, "name":"Slot12Amount"     , "default":64, "isBipolar":true                            },
 		{"index":227, "name":"Slot12Destination", "min":0, "max":30, "isDiscrete":true, "toText":"modDest"  },
 		{"index":228, "name":"Slot13Source"     , "min":0, "max":31, "isDiscrete":true, "toText":"modSource"},
 		{"index":229, "name":"Slot13Amount"     , "default":64, "isBipolar":true                            },
 		{"index":230, "name":"Slot13Destination", "min":0, "max":30, "isDiscrete":true, "toText":"modDest"  },
 		{"index":231, "name":"Slot14Source"     , "min":0, "max":31, "isDiscrete":true, "toText":"modSource"},
 		{"index":232, "name":"Slot14Amount"     , "default":64, "isBipolar":true                            },
 		{"index":233, "name":"Slot14Destination", "min":0, "max":30, "isDiscrete":true, "toText":"modDest"  },
 		{"index":234, "name":"Slot15Source"     , "min":0, "max":31, "isDiscrete":true, "toText":"modSource"},
 		{"index":235, "name":"Slot15Amount"     , "default":64, "isBipolar":true                            },
 		{"index":236, "name":"Slot15Destination", "min":0, "max":30, "isDiscrete":true, "toText":"modDest"  },
 		{"index":237, "name":"Slot16Source"     , "min":0, "max":31, "isDiscrete":true, "toText":"modSource"},
 		{"index":238, "name":"Slot16Amount"     , "default":64, "isBipolar":true                            },
 		{"index":239, "name":"Slot16Destination", "min":0, "max":30, "isDiscrete":true, "toText":"modDest"  },

		// Sound Name
 		{"index":240, "name":"Name00", "min":32, "max":127, "isDiscrete":true, "toText":"ascii"},
 		{"index":241, "name":"Name01", "min":32, "max":127, "isDiscrete":true, "toText":"ascii"},
 		{"index":242, "name":"Name02", "min":32, "max":127, "isDiscrete":true, "toText":"ascii"},
 		{"index":243, "name":"Name03", "min":32, "max":127, "isDiscrete":true, "toText":"ascii"},
 		{"index":244, "name":"Name04", "min":32, "max":127, "isDiscrete":true, "toText":"ascii"},
 		{"index":245, "name":"Name05", "min":32, "max":127, "isDiscrete":true, "toText":"ascii"},
 		{"index":246, "name":"Name06", "min":32, "max":127, "isDiscrete":true, "toText":"ascii"},
 		{"index":247, "name":"Name07", "min":32, "max":127, "isDiscrete":true, "toText":"ascii"},
 		{"index":248, "name":"Name08", "min":32, "max":127, "isDiscrete":true, "toText":"ascii"},
 		{"index":249, "name":"Name09", "min":32, "max":127, "isDiscrete":true, "toText":"ascii"},
 		{"index":250, "name":"Name10", "min":32, "max":127, "isDiscrete":true, "toText":"ascii"},
 		{"index":251, "name":"Name11", "min":32, "max":127, "isDiscrete":true, "toText":"ascii"},
 		{"index":252, "name":"Name12", "min":32, "max":127, "isDiscrete":true, "toText":"ascii"},
 		{"index":253, "name":"Name13", "min":32, "max":127, "isDiscrete":true, "toText":"ascii"},
 		{"index":254, "name":"Name14", "min":32, "max":127, "isDiscrete":true, "toText":"ascii"},
 		{"index":255, "name":"Name15", "min":32, "max":127, "isDiscrete":true, "toText":"ascii"},

		// MULTI
		
		// GLOBAL
 		{"page":200, "index":12, "class":"Global", "name":"MainVolume"},

		// SOFT KNOBS
		{"page":300, "index":0, "name":"PlayParamValueA", "min":0, "max":127, "isPublic":true, "softknobTargetSelect":"PlayParamA", "softknobTargetList":"playParamTargets"},
		{"page":300, "index":1, "name":"PlayParamValueB", "min":0, "max":127, "isPublic":true, "softknobTargetSelect":"PlayParamB", "softknobTargetList":"playParamTargets"},
		{"page":300, "index":2, "name":"PlayParamValueC", "min":0, "max":127, "isPublic":true, "softknobTargetSelect":"PlayParamC", "softknobTargetList":"playParamTargets"},
		{"page":300, "index":3, "name":"PlayParamValueD", "min":0, "max":127, "isPublic":true, "softknobTargetSelect":"PlayParamD", "softknobTargetList":"playParamTargets"},

		// CONTROLLERS
		{"page":400, "index":0, "name":"ControlW"},
		{"page":400, "index":1, "name":"ControlX"},
		{"page":400, "index":2, "name":"ControlY"},
		{"page":400, "index":3, "name":"ControlZ"}
 	],
 	"valuelists":
 	{
 		"unsignedZero":
 		[
 			"0",	"1",	"2",	"3",	"4",	"5",	"6",	"7",	"8",	"9",	"10",	"11",	"12",	"13",	"14",	"15",	"16",	"17",	"18",	"19",
 			"20",	"21",	"22",	"23",	"24",	"25",	"26",	"27",	"28",	"29",	"30",	"31",	"32",	"33",	"34",	"35",	"36",	"37",	"38",	"39",
 			"40",	"41",	"42",	"43",	"44",	"45",	"46",	"47",	"48",	"49",	"50",	"51",	"52",	"53",	"54",	"55",	"56",	"57",	"58",	"59",			
 			"60",	"61",	"62",	"63",	"64",	"65",	"66",	"67",	"68",	"69",	"70",	"71",	"72",	"73",	"74",	"75",	"76",	"77",	"78",	"79",			
 			"80",	"81",	"82",	"83",	"84",	"85",	"86",	"87",	"88",	"89",	"90",	"91",	"92",	"93",	"94",	"95",	"96",	"97",	"98",	"99",			
 			"100",	"101",	"102",	"103",	"104",	"105",	"106",	"107",	"108",	"109",	"110",	"111",	"112",	"113",	"114",	"115",	"116",	"117",	"118",	"119",			
 			"120",	"121",	"122",	"123",	"124",	"125",	"126",	"127"
 		],
 		"unsignedOne":
 		[
				"1",	"2",	"3",	"4",	"5",	"6",	"7",	"8",	"9",	"10",	"11",	"12",	"13",	"14",	"15",	"16",	"17",	"18",	"19",
 			"20",	"21",	"22",	"23",	"24",	"25",	"26",	"27",	"28",	"29",	"30",	"31",	"32",	"33",	"34",	"35",	"36",	"37",	"38",	"39",
 			"40",	"41",	"42",	"43",	"44",	"45",	"46",	"47",	"48",	"49",	"50",	"51",	"52",	"53",	"54",	"55",	"56",	"57",	"58",	"59",			
 			"60",	"61",	"62",	"63",	"64",	"65",	"66",	"67",	"68",	"69",	"70",	"71",	"72",	"73",	"74",	"75",	"76",	"77",	"78",	"79",			
 			"80",	"81",	"82",	"83",	"84",	"85",	"86",	"87",	"88",	"89",	"90",	"91",	"92",	"93",	"94",	"95",	"96",	"97",	"98",	"99",			
 			"100",	"101",	"102",	"103",	"104",	"105",	"106",	"107",	"108",	"109",	"110",	"111",	"112",	"113",	"114",	"115",	"116",	"117",	"118",	"119",			
 			"120",	"121",	"122",	"123",	"124",	"125",	"126",	"127",	"128"
 		],
 		"signed":
 		[
 			"-64",	"-63",	"-62",	"-61",	
 			"-60",	"-59",	"-58",	"-57",	"-56",	"-55",	"-54",	"-53",	"-52",	"-51",	"-50",	"-49",	"-48",	"-47",	"-46",	"-45", "-44",	"-43",	"-42",	"-41",	
 			"-40",	"-39",	"-38",	"-37",	"-36",	"-35",	"-34",	"-33",	"-32",	"-31",	"-30",	"-29",	"-28",	"-27",	"-26",	"-25",	"-24",	"-23",	"-22",	"-21",
 			"-20",	"-19",	"-18",	"-17",	"-16",	"-15",	"-14",	"-13",	"-12",	"-11",	"-10",	"-9",	"-8",	"-7",	"-6",	"-5",	"-4",	"-3",	"-2",	"-1",
 			"0",	"+1",	"+2",	"+3",	"+4",	"+5",	"+6",	"+7",	"+8",	"+9",	"+10",	"+11",	"+12",	"+13",	"+14",	"+15",	"+16",	"+17",	"+18",	"+19",
 			"+20",	"+21",	"+22",	"+23",	"+24",	"+25",	"+26",	"+27",	"+28",	"+29",	"+30",	"+31",	"+32",	"+33",	"+34",	"+35",	"+36",	"+37",	"+38",	"+39",
 			"+40",	"+41",	"+42",	"+43",	"+44",	"+45",	"+46",	"+47",	"+48",	"+49",	"+50",	"+51",	"+52",	"+53",	"+54",	"+55",	"+56",	"+57",	"+58",	"+59",			
 			"+60",	"+61",	"+62",	"+63"
 		],
		"ascii":
		[
			"NUL","SOH","STX","ETX","EOT","ENQ","ACK","BEL","BS","HT","LF","VT","FF","CR","SO","SI","DLE","DC1","DC2","DC3","DC4","NAK","SYN","ETB","CAN","EM","SUB","ESC","FS","GS","RS","US",
			", ","!","\"","#","$","%","&","'","(",")","*","+",",","-",".","/",
			"0","1","2","3","4","5","6","7","8","9",
			":",";","<","=",">","?","@",
			"A","B","C","D","E","F","G","H","I","J","K","L","M","N","O","P","Q","R","S","T","U","V","W","X","Y","Z",
			"[","\\","]","^","_","`",
			"a","b","c","d","e","f","g","h","i","j","k","l","m","n","o","p","q","r","s","t","u","v","w","x","y","z",
			"{","|","}","~","DEL"
		],
 		"pbrange":
 		[
 			"0",	"1",	"2",	"3",	"4",	"5",	"6",	"7",	"8",	"9",	"10",	"11",	"12",	"13",	"14",	"15",	"16",	"17",	"18",	"19",
 			"20",	"21",	"22",	"23",	"24",	"25",	"26",	"27",	"28",	"29",	"30",	"31",	"32",	"33",	"34",	"35",	"36",	"37",	"38",	"39",
 			"40",	"41",	"42",	"43",	"44",	"45",	"46",	"47",	"48",	"49",	"50",	"51",	"52",	"53",	"54",	"55",	"56",	"57",	"58",	"59",			
 			"60",	"61",	"62",	"63",	"64",	"65",	"66",	"67",	"68",	"69",	"70",	"71",	"72",	"73",	"74",	"75",	"76",	"77",	"78",	"79",			
 			"80",	"81",	"82",	"83",	"84",	"85",	"86",	"87",	"88",	"89",	"90",	"91",	"92",	"93",	"94",	"95",	"96",	"97",	"98",	"99",			
 			"100",	"101",	"102",	"103",	"104",	"105",	"106",	"107",	"108",	"109",	"110",	"111",	"112",	"113",	"114",	"115",	"116",	"117",	"118",	"119",			
 			"120",	"harmonic", "global"
 		],
		"offOn":
		[
			"Off", "On"
		],
		"waveType":
		[
			"Resonant", "Resonant 2", "Mallet Syn", "Square-Sweep", "Bellish", "Pulse-Sweep", "Saw-Sweep", "Mellow Saw", 
			"Feedback", "Add Harm", "Reso 3 HP", "Wind Syn", "High Harm", "Clipper", "Organ Syn", "Square Saw", 
			"Formant 1", "Polated", "Transient", "E Piano", "Robotic", "Strong Harm", "Perc Organ", "Clip Sweep", 
			"Reso Harms", "2 Echoes", "Formant 2", "Formant Vocal", "Micro Sync", "Micro PWM", "Glassy", "Square HP", 
			"Saw Sync 1", "Saw Sync 2", "Saw Sync 3", "Pul Sync 1", "Pul Sync 2", "Pul Sync 3", "Sin Sync 1", "Sin Sync 2", 
			"Sin Sync 3", "PWM Pulse", "PWM Saw", "Fuzz Wave", "Distorted", "Heavy Fuzz", "Fuzz Sync", "K+Strong 1", 
			"K+Strong 2", "K+Strong 3", "1-2-3-4-5", "19/twenty", "Wavetrip 1", "Wavetrip 2", "Wavetrip 3", "Wavetrip 4", 
			"Male Voice", "Low Piano", "Reso Sweep", "Xmas Bell", "FM Piano", "Fat Organ", "Vibes", "Chorus 2", 
			"True PWM", 
			"", "", "", "", "", "", "", "", 
			"", "", "", "", "", "", "", "", 
			"", "", "", "", "", "", "", "", 
			"", "", "", "", "", "", "", 
			"User 1", "User 2", "User 3", "User 4", "User 5", "User 6", "User 7", "User 8", 
			"User 9", "User 10", "User 11", "User 12", "User 13", "User 14", "User 15", "User 16", 
			"User 17", "User 18", "User 19", "User 20", "User 21", "User 22", "User 23", "User 24", 
			"User 25", "User 26", "User 27", "User 28", "User 29", "User 30", "User 31", "User 32"
		],
		"waveStartWave":
		[
 			"0",	"1",	"2",	"3",	"4",	"5",	"6",	"7",	"8",	"9",	"10",	"11",	"12",	"13",	"14",	"15",	"16",	"17",	"18",	"19",
 			"20",	"21",	"22",	"23",	"24",	"25",	"26",	"27",	"28",	"29",	"30",	"31",	"32",	"33",	"34",	"35",	"36",	"37",	"38",	"39",
 			"40",	"41",	"42",	"43",	"44",	"45",	"46",	"47",	"48",	"49",	"50",	"51",	"52",	"53",	"54",	"55",	"56",	"57",	"58",	"59",			
 			"60",	"Tri",	"Sqr",	"Saw"
		],
		// TODO
 		"waveStartPhase":
 		[
 			"free",	"1",	"2",	"3",	"4",	"5",	"6",	"7",	"8",	"9",	"10",	"11",	"12",	"13",	"14",	"15",	"16",	"17",	"18",	"19",
 			"20",	"21",	"22",	"23",	"24",	"25",	"26",	"27",	"28",	"29",	"30",	"31",	"32",	"33",	"34",	"35",	"36",	"37",	"38",	"39",
 			"40",	"41",	"42",	"43",	"44",	"45",	"46",	"47",	"48",	"49",	"50",	"51",	"52",	"53",	"54",	"55",	"56",	"57",	"58",	"59",			
 			"60",	"61",	"62",	"63",	"64",	"65",	"66",	"67",	"68",	"69",	"70",	"71",	"72",	"73",	"74",	"75",	"76",	"77",	"78",	"79",			
 			"80",	"81",	"82",	"83",	"84",	"85",	"86",	"87",	"88",	"89",	"90",	"91",	"92",	"93",	"94",	"95",	"96",	"97",	"98",	"99",			
 			"100",	"101",	"102",	"103",	"104",	"105",	"106",	"107",	"108",	"109",	"110",	"111",	"112",	"113",	"114",	"115",	"116",	"117",	"118",	"119",			
 			"120",	"121",	"122",	"123",	"124",	"125",	"126",	"127"
 		],
		"aliasing":
		[
			"off", "1", "2", "3", "4", "5"
		],
		"timeQuant":
		[
			"off", "1", "2", "3", "4", "5"
		],
		"clipping":
		[
			"Saturate", "Overflow"
		],
		"accuracy":
		[
			"Off", "On"
		],
		"playParameter":
		[
			"Osc 1 Octave", "Osc 1 Semitone", "Osc 1 Detune", "Osc 1 Pitchbend", "Osc 1 Keytrack", 
			"Osc 2 Octave", "Osc 2 Semitone", "Osc 2 Detune", "Osc 2 Pitchbend", "Osc 2 Keytrack", 
			"Wavetable", 
			"Wave 1 Startwave", "Wave 1 Phase", "Wave 1 Env Amount", "Wave 1 Velo Amount", "Wave 1 Keytrack", 
			"Wave 2 Startwave", "Wave 2 Phase", "Wave 2 Env Amount", "Wave 2 Velo Amount", "Wave 2 Keytrack", 
			"Mix Wave 1", "Mix Wave 2", "Mix Ringmod", "Mix Noise", 
			"Aliasing", "Quantize", "Clipping", 
			"Filter 1 Cutoff", "Filter 1 Resonance", "Filter 1 Type", "Filter 1 Keytrack", "Filter 1 Env Amount", "Filter 1 Velo Amount", 
			"Filter 2 Cutoff", "Filter 2 Type", "Filter 2 Keytrack", 
			"Sound Volume", "Amp Envelope Velo Amount", "Amplifier Keytrack", 
			"Chorus",
			"Panning", 
			"Pan Keytrack",
			"Glide on/off", "Glide Type", 
			"Arpeggiator on/off/hold", "Arp Tempo", "Arp Clock", "Arp Range", "Arp Pattern", "Arp Direction", "Arp Note Order", "Arp Velocity", 
			"Allocation", "Assignment", 
			"Filter Env Attack", "Filter Env Decay", "Filter Env Sustain", "Filter Env Release", 
			"Amlifier Env Attack", "Amlifier Env Decay", "Amplifier Env Sustain", "Amplifier Env Release", 
			"LFO1 Rate", "LFO1 Shape", "LFO1 Delay", "LFO1 Sync", "LFO1 Symmetry", "LFO1 Humanize", 
			"LFO2 Rate", "LFO2 Shape", "LFO2 Delay", "LFO2 Sync", "LFO2 Symmetry", "LFO2 Humanize", "LFO2 Phase", 
			"Osc 1 FM Amount", "Filter 1 Special", "Glide Time", 
			"Control W", "Control X", "Control Y", "Control Z"		
		],
		"playParamTargets":
		[
			"O1Octave", "O1Semi", "O1Detune", "O1BendRange", "O1KeyTrack", 
			"O2Octave", "O2Semi", "O2Detune", "O2BendRange", "O2KeyTrack", 
			"Wave", 
			"W1StartW", "W1StartP", "W1EnvAmount", "W1EnvVelAmount", "W1Keytrack", 
			"W2StartW", "W2StartP", "W2EnvAmount", "W2EnvVelAmount", "W2Keytrack", 
			"MixW1", "MixW2", "MixRingMod", "MixNoise", 
			"Aliasing", "TimeQuant", "Clipping", 
			"F1Cutoff", "F1Resonance", "F1Type", "F1KeyTrack", "F1EnvAmount", "F1EnvVelAmount", 
			"F2Cutoff", "F2Type", "F2KeyTrack", 
			"AmpVolume", "AmpVelocity", "AmpKeytrack", 
			"ChorusEnabled",
			"Pan", 
			"PanKeytrack",
			"GlideEnabled", "GlideEnabled", 
			"ArpMode", "ArpTempo", "ArpClock", "ArpRange", "ArpPattern", "ArpDirection", "ArpNoteOrder", "ArpVelocity", 
			"AllocationMode", "Assignment", 
			"F1EnvAttack", "F1EnvDecay", "F1EnvSustain", "F1EnvRelease", 
			"AmpEnvAttack", "AmpEnvDecay", "AmpEnvSustain", "AmpEnvRelease", 
			"Lfo1Rate", "Lfo1Shape", "Lfo1Delay", "Lfo1Sync", "Lfo1Symmetry", "Lfo1Humanize", 
			"Lfo2Rate", "Lfo2Shape", "Lfo2Delay", "Lfo2Sync", "Lfo2Symmetry", "Lfo2Humanize", "Lfo2Phase", 
			"O1FmAmount", "F1ContextSensitive", "GlideTime", 
			"ControlW", "ControlX", "ControlY", "ControlZ"		
		],
		"filter1Type":
		[
			"24 dB LP", "12 dB LP", "24 dB BP", "12 dB BP", 
			"12 dB HP", "Sine WS => 12 dB LP", "12 dB LP => WS", "12 dB LP/BP", 
			"12 dB LP FM", "12 dB LP S&H"
		],
		"filter2Type":
		[
			"6 dB LP", "6 dB HP"
		],
		"effectType":
		[
			"Off", "Chorus", "Flanger 1", "Flanger 2", "AutoWah LP", "AutoWah BP", "Overdrive", "Amp. Mod", "", "", "",
			"", "", "", "", "", "", "", "", "", "", "", "", "", "", "", "", "", "", "", "", "", "Delay", "Pan Delay", "Mod Delay"
		],
 		"pan":
 		[
 			"Left",	"-63",	"-62",	"-61",	
 			"-60",	"-59",	"-58",	"-57",	"-56",	"-55",	"-54",	"-53",	"-52",	"-51",	"-50",	"-49",	"-48",	"-47",	"-46",	"-45", "-44",	"-43",	"-42",	"-41",	
 			"-40",	"-39",	"-38",	"-37",	"-36",	"-35",	"-34",	"-33",	"-32",	"-31",	"-30",	"-29",	"-28",	"-27",	"-26",	"-25",	"-24",	"-23",	"-22",	"-21",
 			"-20",	"-19",	"-18",	"-17",	"-16",	"-15",	"-14",	"-13",	"-12",	"-11",	"-10",	"-9",	"-8",	"-7",	"-6",	"-5",	"-4",	"-3",	"-2",	"-1",
 			"Center","+1",	"+2",	"+3",	"+4",	"+5",	"+6",	"+7",	"+8",	"+9",	"+10",	"+11",	"+12",	"+13",	"+14",	"+15",	"+16",	"+17",	"+18",	"+19",
 			"+20",	"+21",	"+22",	"+23",	"+24",	"+25",	"+26",	"+27",	"+28",	"+29",	"+30",	"+31",	"+32",	"+33",	"+34",	"+35",	"+36",	"+37",	"+38",	"+39",
 			"+40",	"+41",	"+42",	"+43",	"+44",	"+45",	"+46",	"+47",	"+48",	"+49",	"+50",	"+51",	"+52",	"+53",	"+54",	"+55",	"+56",	"+57",	"+58",	"+59",			
 			"+60",	"+61",	"+62",	"Right"
 		],
		"glideType":
		[
			"Portamento", "Glissando", "Fingered Porta", "Glissando", "Fingered Gliss."
		],
		"glideMode":
		[
			"Exp", "Linear"
		],
		"arpMode":
		[
			"Off", "On", "Hold"
		],
		// TODO
		"arpTempo":
		[
			"40", "42", "44", "46", "48", 
			"50", "52", "54", "56", "58", 
			"60", "62", "64", "66", "68", 
			"70", "72", "74", "76", "78", 
			"80", "82", "84", "86", "88", 
			"90",
			"91",	"92",	"93",	"94",	"95",	"96",	"97",	"98",	"99",
 			"100",	"101",	"102",	"103",	"104",	"105",	"106",	"107",	"108",	"109",	
			"110",	"111",	"112",	"113",	"114",	"115",	"116",	"117",	"118",	"119",
 			"120",	"121",	"122",	"123",	"124",	"125",	"126",	"127",	"128",	"129",
 			"130",	"131",	"132",	"133",	"134",	"135",	"136",	"137",	"138",	"139",
 			"140",	"141",	"142",	"143",	"144",	"145",	"146",	"147",	"148",	"149",
 			"150",	"151",	"152",	"153",	"154",	"155",	"156",	"157",	"158",	"159",
 			"160",	"161",	"162",	"163",	"164",
			"165",	"170",	"175",	"180",	"185",	"190",	"195",
			"200",	"205",	"210",	"215",	"220",	"225",	"230",	"235",	"240",	"245",
			"250",	"255",	"260",	"265",	"270",	"275",	"280",	"285",	"290",	"295",
			"300"
		],
		"arpClock":
		[
			"1/1", "1/2.", "1/2T", "1/2", 
			"1/4.", "1/4T", "1/4", "1/8.", 
			"1/8T", "1/8", "1/16.", "1/16T", 
			"1/16", "1/32.", "1/32T", "1/32"
		],
		"arpPattern":
		[
			"Off", "User", "1", "2", "3", "4", "5", "6", "7", "8", "9", "10", "11", "12", "13", "14", "15"
		],
		"arpDirection":
		[
			"Up", "Down", "Alt", "Random"
		],
		"arpNoteOrder":
		[
			"Note", "N. Reversed", "As Played", "P. Reversed"
		],
		"arpVelocity":
		[
			"Root Note", "Last Note"
		],
		"arpUserPatternBits":
		[
			"---", "---*", "--*-", "--**",
			"-*-", "-*-*", "-**-", "-***",
			"*--", "*--*", "*-*-", "*-**",
			"**-", "**-*", "***-", "****"
		],
		"allocationMode":
		[
			"Poly", "Mono"
		],
		"assignment":
		[
			"Normal", "Dual", "Unisono"
		],
		"envTrigger":
		[
			"Normal", "Single", "Retriger"
		],
		"lfoShape":
		[
			"Sine", "Triangle", "Square", "Saw", "Random", "S&H"
		],
		"lfoSync":
		[
			"Off", "On", "On", "Clock"
		],
		// TODO
		"lfoPhase":
		[
 			"0",	"1",	"2",	"3",	"4",	"5",	"6",	"7",	"8",	"9",	"10",	"11",	"12",	"13",	"14",	"15",	"16",	"17",	"18",	"19",
 			"20",	"21",	"22",	"23",	"24",	"25",	"26",	"27",	"28",	"29",	"30",	"31",	"32",	"33",	"34",	"35",	"36",	"37",	"38",	"39",
 			"40",	"41",	"42",	"43",	"44",	"45",	"46",	"47",	"48",	"49",	"50",	"51",	"52",	"53",	"54",	"55",	"56",	"57",	"58",	"59",			
 			"60",	"61",	"62",	"63",	"64",	"65",	"66",	"67",	"68",	"69",	"70",	"71",	"72",	"73",	"74",	"75",	"76",	"77",	"78",	"79",			
 			"80",	"81",	"82",	"83",	"84",	"85",	"86",	"87",	"88",	"89",	"90",	"91",	"92",	"93",	"94",	"95",	"96",	"97",	"98",	"99",			
 			"100",	"101",	"102",	"103",	"104",	"105",	"106",	"107",	"108",	"109",	"110",	"111",	"112",	"113",	"114",	"115",	"116",	"117",	"118",	"119",			
 			"120",	"121",	"122",	"123",	"124",	"125",	"126",	"127"
		],
		"modSource":
		[
			"Off", "LFO1", "LFO1 * MW", "LFO1 * AT", "LFO2", "Filter Env", "Amp Env", "Wave Env", "Free Env", "Key Follow", "Keytrack", "Velocity", "Release Vel", "Aftertouch", "Poly Pressure", "Pitch Bend", 
			"Modwheel", "Sustain Control", "Foot Control", "Breath Control", "Control W", "Control X", "Control Y", "Control Z", "Control Delay", "Modifier #1", "Modifier #2", "Modifier #3", "Modifier #4", 
			"MIDI Clock", "min", "MAX"
		],
		"modType":
		[
			"+", "-", "*", "/", "XOR", "OR", "AND", "S&H", "Ramp", "Switch", "Abs", "min", "MAX", "Lag", "Control Proc.", "Diff"
		],
		"modDest":
		[
			"Pitch", "Osc 1 Pitch", "Osc 2 Pitch", "Wave 1 Pos", "Wave 2 Pos", "Mix Wave 1", "Mix Wave 2", "Mix Ring Mod", "Mix Noise", "Filter 1 Cutoff", "Filter 1 Resonance", "Filter 2 Cutoff", 
			"Volume", "Pan", "Filter Env Attack", "Filter Env Decay", "Filter Env Sustain", "Filter Env Release", "Amp Env Attack", "Amp Env Decay", "Amp Env Sustain", "Amp Env Release", 
			"Wave Env Times", "Wave Env Levels", "Free Env Times", "Free Env Levels", "LFO1 Rate", "LFO1 Level", "LFO2 Rate", "LFO2 Level", "Mod #1 Amount", "Mod #2 Amount", "Mod #3 Amount", 
			"Mod #4 Amount", "FM Amount", "F1 Extra"
		],
		"midiChannel":
		[
			"Global", "Omni", "1", "2", "3", "4", "5", "6", "7", "8", "9", "10", "11", "12", "13", "14", "15", "16"
		],
		"output":
		[
			"Main", "Sub"
		],
		"midiNote":
		[
			"C-2","C#-2","D-2","D#-2","E-2","F-2","F#-2","G-2","G#-2","A-2","A#-2","B-2",
			"C-1","C#-1","D-1","D#-1","E-1","F-1","F#-1","G-1","G#-1","A-1","A#-1","B-1",
			"C0", "C#0", "D0", "D#0", "E0", "F0", "F#0", "G0", "G#0", "A0", "A#0", "B0",
			"C1", "C#1", "D1", "D#1", "E1", "F1", "F#1", "G1", "G#1", "A1", "A#1", "B1",
			"C2", "C#2", "D2", "D#2", "E2", "F2", "F#2", "G2", "G#2", "A2", "A#2", "B2",
			"C3", "C#3", "D3", "D#3", "E3", "F3", "F#3", "G3", "G#3", "A3", "A#3", "B3",
			"C4", "C#4", "D4", "D#4", "E4", "F4", "F#4", "G4", "G#4", "A4", "A#4", "B4",
			"C5", "C#5", "D5", "D#5", "E5", "F5", "F#5", "G5", "G#5", "A5", "A#5", "B5",
			"C6", "C#6", "D6", "D#6", "E6", "F6", "F#6", "G6", "G#6", "A6", "A#6", "B6",
			"C7", "C#7", "D7", "D#7", "E7", "F7", "F#7", "G7", "G#7", "A7", "A#7", "B7",
			"C8", "C#8", "D8", "D#8", "E8", "F8", "F#8", "G8"
		],

		// TODO
		"keytrack76":
		[
			"-200%", "-197%", "-194%", "-191%", "-188%", "-185%", "-182%", "-179%",
			"-175%", "-172%", "-169%", "-166%", "-163%", "-160%", "-157%", "-154%",
			"-150%", "-147%", "-144%", "-141%", "-138%", "-135%", "-132%", "-129%",
			"-125%", "-122%", "-119%", "-116%", "-113%", "-110%", "-107%", "-104%",
			"-100%", "-97%", "-94%", "-91%", "-88%", "-85%", "-82%", "-79%",
			"-75%", "-72%", "-69%", "-66%", "-63%", "-60%", "-57%", "-54%",
			"-50%", "-47%", "-44%", "-41%", "-38%", "-35%", "-32%", "-29%",
			"-25%", "-22%", "-19%", "-16%", "-13%", "-10%", "-7%", "-4%",
			"0%", "+3%", "+6%", "+9%", "+12%", "+15%", "+18%", "+21%",
			"+25%", "+28%", "+31%", "+34%", "+37%", "+40%", "+43%", "+46%",
			"+50%", "+53%", "+56%", "+59%", "+62%", "+65%", "+68%", "+71%",
			"+75%", "+78%", "+81%", "+84%", "+87%", "+90%", "+93%", "+96%",
			"+100%", "+103%", "+106%", "+109%", "+112%", "+115%", "+118%", "+121%",
			"+125%", "+128%", "+131%", "+134%", "+137%", "+140%", "+143%", "+146%",
			"+150%", "+153%", "+156%", "+159%", "+162%", "+165%", "+168%", "+171%",
			"+175%", "+178%", "+181%", "+184%", "+187%", "+190%", "+193%", "+197%"
		],
		"keytrack127":
		[
			"-200%", "-197%", "-194%", "-191%", "-188%", "-185%", "-182%", "-179%",
			"-175%", "-172%", "-169%", "-166%", "-163%", "-160%", "-157%", "-154%",
			"-150%", "-147%", "-144%", "-141%", "-138%", "-135%", "-132%", "-129%",
			"-125%", "-122%", "-119%", "-116%", "-113%", "-110%", "-107%", "-104%",
			"-100%", "-97%", "-94%", "-91%", "-88%", "-85%", "-82%", "-79%",
			"-75%", "-72%", "-69%", "-66%", "-63%", "-60%", "-57%", "-54%",
			"-50%", "-47%", "-44%", "-41%", "-38%", "-35%", "-32%", "-29%",
			"-25%", "-22%", "-19%", "-16%", "-13%", "-10%", "-7%", "-4%",
			"0%", "+3%", "+6%", "+9%", "+12%", "+15%", "+18%", "+21%",
			"+25%", "+28%", "+31%", "+34%", "+37%", "+40%", "+43%", "+46%",
			"+50%", "+53%", "+56%", "+59%", "+62%", "+65%", "+68%", "+71%",
			"+75%", "+78%", "+81%", "+84%", "+87%", "+90%", "+93%", "+96%",
			"+100%", "+103%", "+106%", "+109%", "+112%", "+115%", "+118%", "+121%",
			"+125%", "+128%", "+131%", "+134%", "+137%", "+140%", "+143%", "+146%",
			"+150%", "+153%", "+156%", "+159%", "+162%", "+165%", "+168%", "+171%",
			"+175%", "+178%", "+181%", "+184%", "+187%", "+190%", "+193%", "+197%"
		]
	},
 	"midipackets":
 	{
		"requestsingle": [
			{"type": "byte", "value": "f0"},
			{"type": "byte", "value": "3e"},
			{"type": "byte", "value": "0e"},
			{"type": "deviceid"},
			{"type": "byte", "value": "00"},
			{"type": "bank"},
			{"type": "program"},
			{"type": "byte", "value": "f7"}
		],
		"requestmulti": [
			{"type": "byte", "value": "f0"},
			{"type": "byte", "value": "3e"},
			{"type": "byte", "value": "0e"},
			{"type": "deviceid"},
			{"type": "byte", "value": "01"},
			{"type": "bank"},
			{"type": "program"},
			{"type": "byte", "value": "f7"}
		],
		"requestsinglebank": [
			{"type": "byte", "value": "f0"},
			{"type": "byte", "value": "3e"},
			{"type": "byte", "value": "0e"},
			{"type": "deviceid"},
			{"type": "byte", "value": "00"},
			{"type": "byte", "value": "10"},
			{"type": "bank"},
			{"type": "byte", "value": "f7"}
		],
		"requestmultibank": [
			{"type": "byte", "value": "f0"},
			{"type": "byte", "value": "3e"},
			{"type": "byte", "value": "0e"},
			{"type": "deviceid"},
			{"type": "byte", "value": "01"},
			{"type": "byte", "value": "10"},
			{"type": "bank"},
			{"type": "byte", "value": "f7"}
		],
		"requestglobal": [
			{"type": "byte", "value": "f0"},
			{"type": "byte", "value": "3e"},
			{"type": "byte", "value": "0e"},
			{"type": "deviceid"},
			{"type": "byte", "value": "04"},
			{"type": "byte", "value": "f7"}
		],
		"requestmode": [
			{"type": "byte", "value": "f0"},
			{"type": "byte", "value": "3e"},
			{"type": "byte", "value": "0e"},
			{"type": "deviceid"},
			{"type": "byte", "value": "07"},
			{"type": "byte", "value": "f7"}
		],
		"requestallsingles": [
			{"type": "byte", "value": "f0"},
			{"type": "byte", "value": "3e"},
			{"type": "byte", "value": "0e"},
			{"type": "deviceid"},
			{"type": "byte", "value": "00"},
			{"type": "byte", "value": "10"},
			{"type": "byte", "value": "00"},
			{"type": "byte", "value": "f7"}
		],
		"singleparameterchange": [
			{"type": "byte", "value": "f0"},
			{"type": "byte", "value": "3e"},
			{"type": "byte", "value": "0e"},
			{"type": "deviceid"},
			{"type": "byte", "value": "20"},
			{"type": "part"},
			{"type": "page"},
			{"type": "paramindex"},
			{"type": "paramvalue"},
			{"type": "byte", "value": "f7"}
		],
		"multiparameterchange": [
			{"type": "byte", "value": "f0"},
			{"type": "byte", "value": "3e"},
			{"type": "byte", "value": "0e"},
			{"type": "deviceid"},
			{"type": "byte", "value": "21"},
			{"type": "page"},
			{"type": "paramindex"},
			{"type": "paramvalue"},
			{"type": "byte", "value": "f7"}
		],
		"globalparameterchange": [
			{"type": "byte", "value": "f0"},
			{"type": "byte", "value": "3e"},
			{"type": "byte", "value": "0e"},
			{"type": "deviceid"},
			{"type": "byte", "value": "24"},
			{"type": "paramindex"},
			{"type": "paramvalue"},
			{"type": "byte", "value": "f7"}
		],
		"singledump": [
			{"type": "byte", "value": "f0"},
			{"type": "byte", "value": "3e"},
			{"type": "byte", "value": "0e"},
			{"type": "deviceid"},
			{"type": "byte", "value": "10"},
			{"type": "bank"},
			{"type": "program"},

			{"type": "param", "name": "Version"},					// 0
			{"type": "param", "name": "O1Octave"},					// 1
			{"type": "param", "name": "O1Semi"},                                    // 2
			{"type": "param", "name": "O1Detune"},                                  // 3 
			{"type": "null"},                                                       // 4
			{"type": "param", "name": "O1BendRange"},                               // 5
			{"type": "param", "name": "O1KeyTrack"},                                // 6
			{"type": "param", "name": "O1FmAmount"},                                // 7
			{"type": "null"},                                                       // 9
			{"type": "null"},                                                       // 9
			{"type": "null"},                                                       // 10
			{"type": "null"},                                                       // 11
			{"type": "param", "name": "O2Octave"},                                  // 12
			{"type": "param", "name": "O2Semi"},                                    // 13
			{"type": "param", "name": "O2Detune"},                                  // 14
			{"type": "null"},                                                       // 15
			{"type": "param", "name": "O2Sync"},                                    // 16
			{"type": "param", "name": "O2BendRange"},                               // 17
			{"type": "param", "name": "O2KeyTrack"},                                // 18
			{"type": "param", "name": "O2Link"},                                    // 19
			{"type": "null"},                			                // 20
			{"type": "null"},                                                       //
			{"type": "null"},                                                       //
			{"type": "null"},                                                       //
			{"type": "null"},                                                       //
			{"type": "param", "name": "Wave"},                                      //
			{"type": "param", "name": "W1StartW"},                                  //
			{"type": "param", "name": "W1StartP"},
			{"type": "param", "name": "W1EnvAmount"},
			{"type": "param", "name": "W1EnvVelAmount"},
			{"type": "param", "name": "W1Keytrack"},
			{"type": "param", "name": "W1Limit"},
			{"type": "null"},
			{"type": "null"},
			{"type": "null"},
			{"type": "null"},
			{"type": "param", "name": "W2StartW"},
			{"type": "param", "name": "W2StartP"},
			{"type": "param", "name": "W2EnvAmount"},
			{"type": "param", "name": "W2EnvVelAmount"},
			{"type": "param", "name": "W2Keytrack"},
			{"type": "param", "name": "W2Limit"},
			{"type": "param", "name": "W2Link"},
			{"type": "null"},
			{"type": "null"},
			{"type": "null"},
			{"type": "null"},
			{"type": "param", "name": "MixW1"},
			{"type": "param", "name": "MixW2"},
			{"type": "param", "name": "MixRingMod"},
			{"type": "param", "name": "MixNoise"},
			{"type": "param", "name": "MixExternal"},
			{"type": "null"},
			{"type": "param", "name": "Aliasing"},
			{"type": "param", "name": "TimeQuant"},
			{"type": "param", "name": "Clipping"},
			{"type": "null"},
			{"type": "param", "name": "Accuracy"},
			{"type": "param", "name": "PlayParamA"},
			{"type": "param", "name": "PlayParamB"},
			{"type": "param", "name": "PlayParamC"},
			{"type": "param", "name": "PlayParamD"},
			{"type": "param", "name": "F1Cutoff"},
			{"type": "param", "name": "F1Resonance"},
			{"type": "param", "name": "F1Type"},
			{"type": "param", "name": "F1KeyTrack"},
			{"type": "param", "name": "F1EnvAmount"},
			{"type": "param", "name": "F1EnvVelAmount"},
			{"type": "null"},
			{"type": "null"},
			{"type": "param", "name": "F1ContextSensitive"},
			{"type": "null"},
			{"type": "null"},
			{"type": "param", "name": "F2Cutoff"},
			{"type": "param", "name": "F2Type"},
			{"type": "param", "name": "F2KeyTrack"},
			{"type": "param", "name": "EffectType"},
			{"type": "param", "name": "AmpVolume"},
			{"type": "null"},
			{"type": "param", "name": "AmpVelocity"},
			{"type": "param", "name": "AmpKeytrack"},
			{"type": "param", "name": "EffectParamA"},
			{"type": "param", "name": "ChorusEnabled"},
			{"type": "param", "name": "EffectParamB"},
			{"type": "param", "name": "Pan"},
			{"type": "param", "name": "PanKeytrack"},
			{"type": "param", "name": "EffectParamC"},
			{"type": "param", "name": "GlideEnabled"},
			{"type": "param", "name": "GlideType"},
			{"type": "param", "name": "GlideMode"},
			{"type": "param", "name": "GlideTime"},
			{"type": "null"},
			{"type": "param", "name": "ArpMode"},
			{"type": "param", "name": "ArpTempo"},
			{"type": "param", "name": "ArpClock"},
			{"type": "param", "name": "ArpRange"},
			{"type": "param", "name": "ArpPattern"},
			{"type": "param", "name": "ArpDirection"},
			{"type": "param", "name": "ArpNoteOrder"},
			{"type": "param", "name": "ArpVelocity"},
			{"type": "param", "name": "ArpReset"},
			{"type": "param", "name": "ArpUserPatternLength"},
			{"type": "param", "name": "ArpUserPattern1" , "mask":1, "shift":3},
			{"type": "param", "name": "ArpUserPattern2" , "mask":1, "shift":2},
			{"type": "param", "name": "ArpUserPattern3" , "mask":1, "shift":1},
			{"type": "param", "name": "ArpUserPattern4" , "mask":1, "shift":0},
			{"type": "param", "name": "ArpUserPattern5" , "mask":1, "shift":3},
			{"type": "param", "name": "ArpUserPattern6" , "mask":1, "shift":2},
			{"type": "param", "name": "ArpUserPattern7" , "mask":1, "shift":1},
			{"type": "param", "name": "ArpUserPattern8" , "mask":1, "shift":0},
			{"type": "param", "name": "ArpUserPattern9" , "mask":1, "shift":3},
			{"type": "param", "name": "ArpUserPattern10", "mask":1, "shift":2},
			{"type": "param", "name": "ArpUserPattern11", "mask":1, "shift":1},
			{"type": "param", "name": "ArpUserPattern12", "mask":1, "shift":0},
			{"type": "param", "name": "ArpUserPattern13", "mask":1, "shift":3},
			{"type": "param", "name": "ArpUserPattern14", "mask":1, "shift":2},
			{"type": "param", "name": "ArpUserPattern15", "mask":1, "shift":1},
			{"type": "param", "name": "ArpUserPattern16", "mask":1, "shift":0},
			{"type": "null"},
			{"type": "null"},
			{"type": "param", "name": "AllocationMode"},
			{"type": "param", "name": "Assignment"},
			{"type": "param", "name": "Detune"},
			{"type": "null"},
			{"type": "param", "name": "DePan"},
			{"type": "param", "name": "F1EnvAttack"},
			{"type": "param", "name": "F1EnvDecay"},
			{"type": "param", "name": "F1EnvSustain"},
			{"type": "param", "name": "F1EnvRelease"},
			{"type": "param", "name": "F1EnvTrigger"},
			{"type": "null"},
			{"type": "param", "name": "AmpEnvAttack"},
			{"type": "param", "name": "AmpEnvDecay"},
			{"type": "param", "name": "AmpEnvSustain"},
			{"type": "param", "name": "AmpEnvRelease"},
			{"type": "param", "name": "AmpEnvTrigger"},
			{"type": "null"},
			{"type": "param", "name": "WaveEnvTime1"},
			{"type": "param", "name": "WaveEnvLevel1"},
			{"type": "param", "name": "WaveEnvTime2"},
			{"type": "param", "name": "WaveEnvLevel2"},
			{"type": "param", "name": "WaveEnvTime3"},
			{"type": "param", "name": "WaveEnvLevel3"},
			{"type": "param", "name": "WaveEnvTime4"},
			{"type": "param", "name": "WaveEnvLevel4"},
			{"type": "param", "name": "WaveEnvTime5"},
			{"type": "param", "name": "WaveEnvLevel5"},
			{"type": "param", "name": "WaveEnvTime6"},
			{"type": "param", "name": "WaveEnvLevel6"},
			{"type": "param", "name": "WaveEnvTime7"},
			{"type": "param", "name": "WaveEnvLevel7"},
			{"type": "param", "name": "WaveEnvTime8"},
			{"type": "param", "name": "WaveEnvLevel8"},
			{"type": "param", "name": "WaveEnvTrigger"},
			{"type": "param", "name": "WaveKeyOnLoop"},
			{"type": "param", "name": "WaveKeyOnLoopStart"},
			{"type": "param", "name": "WaveKeyOnLoopEnd"},
			{"type": "param", "name": "WaveKeyOffLoop"},
			{"type": "param", "name": "WaveKeyOffLoopStart"},
			{"type": "param", "name": "WaveKeyOffLoopEnd"},
			{"type": "null"},
			{"type": "param", "name": "FreeEnvTime1"},
			{"type": "param", "name": "FreeEnvLevel1"},
			{"type": "param", "name": "FreeEnvTime2"},
			{"type": "param", "name": "FreeEnvLevel2"},
			{"type": "param", "name": "FreeEnvTime3"},
			{"type": "param", "name": "FreeEnvLevel3"},
			{"type": "param", "name": "FreeEnvReleaseTime"},
			{"type": "param", "name": "FreeEnvReleaseLevel"},
			{"type": "param", "name": "FreeEnvTrigger"},
			{"type": "null"},
			{"type": "param", "name": "Lfo1Rate"},
			{"type": "param", "name": "Lfo1Shape"},
			{"type": "param", "name": "Lfo1Delay"},
			{"type": "param", "name": "Lfo1Sync"},
			{"type": "param", "name": "Lfo1Symmetry"},
			{"type": "param", "name": "Lfo1Humanize"},
			{"type": "null"},
			{"type": "param", "name": "Lfo2Rate"},
			{"type": "param", "name": "Lfo2Shape"},
			{"type": "param", "name": "Lfo2Delay"},
			{"type": "param", "name": "Lfo2Sync"},
			{"type": "param", "name": "Lfo2Symmetry"},
			{"type": "param", "name": "Lfo2Humanize"},
			{"type": "param", "name": "Lfo2Phase"},
			{"type": "null"},
			{"type": "param", "name": "ModDelaySource"},
			{"type": "param", "name": "ModDelayTime"},
			{"type": "param", "name": "Mod1Source1"},
			{"type": "param", "name": "Mod1Source2"},
			{"type": "param", "name": "Mod1Type"},
			{"type": "param", "name": "Mod1Parameter"},
			{"type": "param", "name": "Mod2Source1"},
			{"type": "param", "name": "Mod2Source2"},
			{"type": "param", "name": "Mod2Type"},
			{"type": "param", "name": "Mod2Parameter"},
			{"type": "param", "name": "Mod3Source1"},
			{"type": "param", "name": "Mod3Source2"},
			{"type": "param", "name": "Mod3Type"},
			{"type": "param", "name": "Mod3Parameter"},
			{"type": "param", "name": "Mod4Source1"},
			{"type": "param", "name": "Mod4Source2"},
			{"type": "param", "name": "Mod4Type"},
			{"type": "param", "name": "Mod4Parameter"},
			{"type": "param", "name": "Slot1Source"      },
			{"type": "param", "name": "Slot1Amount"      },
			{"type": "param", "name": "Slot1Destination" },
			{"type": "param", "name": "Slot2Source"      },
			{"type": "param", "name": "Slot2Amount"      },
			{"type": "param", "name": "Slot2Destination" },
			{"type": "param", "name": "Slot3Source"      },
			{"type": "param", "name": "Slot3Amount"      },
			{"type": "param", "name": "Slot3Destination" },
			{"type": "param", "name": "Slot4Source"      },
			{"type": "param", "name": "Slot4Amount"      },
			{"type": "param", "name": "Slot4Destination" },
			{"type": "param", "name": "Slot5Source"      },
			{"type": "param", "name": "Slot5Amount"      },
			{"type": "param", "name": "Slot5Destination" },
			{"type": "param", "name": "Slot6Source"      },
			{"type": "param", "name": "Slot6Amount"      },
			{"type": "param", "name": "Slot6Destination" },
			{"type": "param", "name": "Slot7Source"      },
			{"type": "param", "name": "Slot7Amount"      },
			{"type": "param", "name": "Slot7Destination" },
			{"type": "param", "name": "Slot8Source"      },
			{"type": "param", "name": "Slot8Amount"      },
			{"type": "param", "name": "Slot8Destination" },
			{"type": "param", "name": "Slot9Source"      },
			{"type": "param", "name": "Slot9Amount"      },
			{"type": "param", "name": "Slot9Destination" },
			{"type": "param", "name": "Slot10Source"     },
			{"type": "param", "name": "Slot10Amount"     },
			{"type": "param", "name": "Slot10Destination"},
			{"type": "param", "name": "Slot11Source"     },
			{"type": "param", "name": "Slot11Amount"     },
			{"type": "param", "name": "Slot11Destination"},
			{"type": "param", "name": "Slot12Source"     },
			{"type": "param", "name": "Slot12Amount"     },
			{"type": "param", "name": "Slot12Destination"},
			{"type": "param", "name": "Slot13Source"     },
			{"type": "param", "name": "Slot13Amount"     },
			{"type": "param", "name": "Slot13Destination"},
			{"type": "param", "name": "Slot14Source"     },
			{"type": "param", "name": "Slot14Amount"     },
			{"type": "param", "name": "Slot14Destination"},
			{"type": "param", "name": "Slot15Source"     },
			{"type": "param", "name": "Slot15Amount"     },
			{"type": "param", "name": "Slot15Destination"},
			{"type": "param", "name": "Slot16Source"     },
			{"type": "param", "name": "Slot16Amount"     },
			{"type": "param", "name": "Slot16Destination"},
			{"type": "param", "name": "Name00"},
			{"type": "param", "name": "Name01"},
			{"type": "param", "name": "Name02"},
			{"type": "param", "name": "Name03"},
			{"type": "param", "name": "Name04"},
			{"type": "param", "name": "Name05"},
			{"type": "param", "name": "Name06"},
			{"type": "param", "name": "Name07"},
			{"type": "param", "name": "Name08"},
			{"type": "param", "name": "Name09"},
			{"type": "param", "name": "Name10"},
			{"type": "param", "name": "Name11"},
			{"type": "param", "name": "Name12"},
			{"type": "param", "name": "Name13"},
			{"type": "param", "name": "Name14"},
			{"type": "param", "name": "Name15"},
			{"type": "checksum", "first": 7, "last": 262},
			{"type": "byte", "value": "f7"}
		],

		"globaldump": [
			{"type": "byte", "value": "f0"},
			{"type": "byte", "value": "3e"},
			{"type": "byte", "value": "0e"},
			{"type": "deviceid"},
			{"type": "byte", "value": "14"},

			{"type": "null"},	 				// Reserved0,
			{"type": "null"},	 				// Version,
			{"type": "null"},	 				// StartupSoundbank,
			{"type": "null"},	 				// StartupSoundNum,
			{"type": "null"},	 				// MidiChannel,
			{"type": "null"},	 				// ProgramChangeMode,
			{"type": "null"},	 				// DeviceId,
			{"type": "null"},	 				// BendRange,
			{"type": "null"},	 				// ControllerW,
			{"type": "null"},	 				// ControllerX,
			{"type": "null"},	 				// ControllerY,
			{"type": "null"},	 				// ControllerZ,
			{"type": "param", "name": "MainVolume"},		// MainVolume,
			{"type": "null"},					// Reserved13,
			{"type": "null"},					// Reserved14,
			{"type": "null"},					// Transpose,
			{"type": "null"},					// MasterTune,
			{"type": "null"},					// DisplayTimeout,
			{"type": "null"},					// LcdContrast,
			{"type": "null"},					// Reserved19,
			{"type": "null"},					// Reserved20,
			{"type": "null"},					// Reserved21,
			{"type": "null"},					// Reserved22,
			{"type": "null"},					// StartupMultiNumber,
			{"type": "null"},					// ArpNoteOutChannel,
			{"type": "null"},					// MidiClockOutput,
			{"type": "null"},					// ParameterSend,
			{"type": "null"},					// ParameterReceive,
			{"type": "null"},					// InputGain,
			{"type": "null"},					// Reserved29,
			{"type": "null"},					// Reserved30,
			{"type": "null"},					// Reserved31

			{"type": "checksum", "first": 5, "last": 37},
			{"type": "byte", "value": "f7"}
		],

		"modedump": [
			{"type": "byte", "value": "f0"},
			{"type": "byte", "value": "3e"},
			{"type": "byte", "value": "0e"},
			{"type": "deviceid"},
			{"type": "byte", "value": "17"},
			{"type": "null"},
			{"type": "byte", "value": "f7"}
		],
		"emuRequestLcd": [
			{"type": "byte", "value": "f0"},
			{"type": "byte", "value": "3e"},
			{"type": "byte", "value": "0e"},
			{"type": "deviceid"},
			{"type": "byte", "value": "60"},
			{"type": "byte", "value": "f7"}
		],
		"emuRequestLeds": [
			{"type": "byte", "value": "f0"},
			{"type": "byte", "value": "3e"},
			{"type": "byte", "value": "0e"},
			{"type": "deviceid"},
			{"type": "byte", "value": "61"},
			{"type": "byte", "value": "f7"}
		],
		"emuSendButton": [
			{"type": "byte", "value": "f0"},
			{"type": "byte", "value": "3e"},
			{"type": "byte", "value": "0e"},
			{"type": "deviceid"},
			{"type": "byte", "value": "62"},
			{"type": "paramindex"},
			{"type": "paramvalue"},
			{"type": "byte", "value": "f7"}
		],
		"emuSendRotary": [
			{"type": "byte", "value": "f0"},
			{"type": "byte", "value": "3e"},
			{"type": "byte", "value": "0e"},
			{"type": "deviceid"},
			{"type": "byte", "value": "63"},
			{"type": "paramindex"},
			{"type": "paramvalue"},
			{"type": "byte", "value": "f7"}
		]
	}
}
